project_explorer/.default_settings.json
project_explorer/__init__.py
project_explorer/__main__.py
project_explorer/default_theme.scss
project_explorer/extended_json.py
project_explorer/extended_tabs.py
project_explorer/file_view_icons.json
project_explorer/json_file_icon_provider.py
project_explorer/path_edit.py
project_explorer/path_utils.py
project_explorer/project_explorer.py
project_explorer/root_widget.py
project_explorer/icons/null.png
project_explorer/icons/a-file-icon/LICENSE.md
project_explorer/icons/a-file-icon/README.md
project_explorer/icons/a-file-icon/package.json
project_explorer/icons/a-file-icon/icons/multi/file_type_access.png
project_explorer/icons/a-file-icon/icons/multi/file_type_actionscript.png
project_explorer/icons/a-file-icon/icons/multi/file_type_ae.png
project_explorer/icons/a-file-icon/icons/multi/file_type_ai.png
project_explorer/icons/a-file-icon/icons/multi/file_type_angular.png
project_explorer/icons/a-file-icon/icons/multi/file_type_applescript.png
project_explorer/icons/a-file-icon/icons/multi/file_type_archive.png
project_explorer/icons/a-file-icon/icons/multi/file_type_audio.png
project_explorer/icons/a-file-icon/icons/multi/file_type_babel.png
project_explorer/icons/a-file-icon/icons/multi/file_type_binary.png
project_explorer/icons/a-file-icon/icons/multi/file_type_blade.png
project_explorer/icons/a-file-icon/icons/multi/file_type_bower.png
project_explorer/icons/a-file-icon/icons/multi/file_type_c.png
project_explorer/icons/a-file-icon/icons/multi/file_type_cf.png
project_explorer/icons/a-file-icon/icons/multi/file_type_circleci.png
project_explorer/icons/a-file-icon/icons/multi/file_type_clojure.png
project_explorer/icons/a-file-icon/icons/multi/file_type_coffeescript.png
project_explorer/icons/a-file-icon/icons/multi/file_type_composer.png
project_explorer/icons/a-file-icon/icons/multi/file_type_cpp.png
project_explorer/icons/a-file-icon/icons/multi/file_type_csharp.png
project_explorer-0.0.0a7.dist-info/DESCRIPTION.rst
project_explorer-0.0.0a7.dist-info/METADATA
project_explorer-0.0.0a7.dist-info/RECORD
project_explorer-0.0.0a7.dist-info/WHEEL
project_explorer-0.0.0a7.dist-info/metadata.json
project_explorer-0.0.0a7.dist-info/top_level.txt
