Metadata-Version: 2.0
Name: project-explorer
Version: 0.0.0a7
Summary: A simple file browser that uses project based concepts.
Home-page: https://github.com/mfish38/project_explorer
Author: Mark Fisher
Author-email: UNKNOWN
License: MIT
Platform: UNKNOWN
Classifier: Intended Audience :: Developers
Classifier: Topic :: Desktop Environment :: File Managers
Classifier: Operating System :: Microsoft :: Windows
Classifier: Programming Language :: Python :: 3.6
Classifier: License :: OSI Approved :: MIT License
Requires-Dist: qtpy
Requires-Dist: ntfsutils
Requires-Dist: pyScss
